config_proxy.py
config_proxy-0.1.5.dist-info/WHEEL
config_proxy-0.1.5.dist-info/METADATA
config_proxy-0.1.5.dist-info/RECORD
